mokeidb/__init__.py
mokeidb/dbmodel.py
mokeidb/decorators.py
mokeidb/enum.py
mokeidb/exceptions.py
mokeidb/field.py
mokeidb/generics.py
mokeidb/mongodb.py
mokeidb/serializer.py
mokeidb/sqlite.py
mokeidb/tests/test_mongodb.py
mokeidb/tests/test_serializer.py
mokeidb-0.1.7.dist-info/METADATA
mokeidb-0.1.7.dist-info/WHEEL
mokeidb-0.1.7.dist-info/RECORD
