Metadata-Version: 2.4
Name: mokeidb
Version: 0.1.7
Summary: Create MongoDB models like creating a dataclass
Project-URL: Homepage, https://github.com/deuxglaces/mokeidb
Project-URL: Issues, https://github.com/deuxglaces/mokeidb/issues
Author-email: deuxglaces <dev@deuxglaces.com>
Classifier: License :: OSI Approved :: MIT License
Classifier: Operating System :: OS Independent
Classifier: Programming Language :: Python :: 3
Requires-Python: >=3.10
Requires-Dist: pymongo>=4.2.0
